quanta/__init__.py
quanta/__main__.py
quanta/api.py
quanta/compiler.py
quanta/errors.py
quanta/ast/__init__.py
quanta/ast/nodes.py
quanta/ast/visitor.py
quanta/cli/__init__.py
quanta/cli/main.py
quanta/ir/__init__.py
quanta/ir/ir_nodes.py
quanta/lexer/__init__.py
quanta/lexer/lexer.py
quanta/lower/__init__.py
quanta/lower/qasm3.py
quanta/parser/__init__.py
quanta/parser/parser.py
quanta/runtime/__init__.py
quanta/runtime/qiskit.py
quanta/sema/__init__.py
quanta/sema/transform.py
quanta/sema/typecheck.py
quanta/sema/validation.py
quanta/stdlib/__init__.py
quanta_lang-0.1.8.dist-info/licenses/LICENSE
quanta_lang-0.1.8.dist-info/METADATA
quanta_lang-0.1.8.dist-info/WHEEL
quanta_lang-0.1.8.dist-info/entry_points.txt
quanta_lang-0.1.8.dist-info/top_level.txt
quanta_lang-0.1.8.dist-info/RECORD
