Metadata-Version: 2.4
Name: quanta-lang
Version: 0.1.8
Summary: Quanta: A high-level language that compiles to OpenQASM 3
Author-email: Quanta Language Contributors <quanta@example.com>
License: MIT License
Project-URL: Homepage, https://github.com/quanta-lang/quanta
Project-URL: Documentation, https://github.com/quanta-lang/quanta/docs
Project-URL: Repository, https://github.com/quanta-lang/quanta
Project-URL: Issues, https://github.com/quanta-lang/quanta/issues
Classifier: Development Status :: 3 - Alpha
Classifier: Intended Audience :: Developers
Classifier: Intended Audience :: Science/Research
Classifier: License :: OSI Approved :: MIT License
Classifier: Programming Language :: Python :: 3
Classifier: Programming Language :: Python :: 3.10
Classifier: Programming Language :: Python :: 3.11
Classifier: Programming Language :: Python :: 3.12
Classifier: Topic :: Scientific/Engineering
Classifier: Topic :: Software Development :: Compilers
Requires-Python: >=3.10
License-File: LICENSE
Requires-Dist: qiskit>=1.0
Requires-Dist: qiskit-qasm3-import>=0.6.0
Requires-Dist: lark>=1.1.9
Provides-Extra: dev
Requires-Dist: pytest>=7.0; extra == "dev"
Requires-Dist: pytest-cov>=4.0; extra == "dev"
Requires-Dist: black>=23.0; extra == "dev"
Requires-Dist: ruff>=0.1.0; extra == "dev"
Dynamic: license-file
